galv/__init__.py
galv/api_client.py
galv/configuration.py
galv/exceptions.py
galv/rest.py
galv/schemas.py
galv/apis/__init__.py
galv/apis/path_to_api.py
galv/apis/tag_to_api.py
galv/apis/paths/__init__.py
galv/apis/paths/access_levels_.py
galv/apis/paths/activate_.py
galv/apis/paths/additional_storage_.py
galv/apis/paths/additional_storage_describe_.py
galv/apis/paths/additional_storage_id_.py
galv/apis/paths/arbitrary_files_.py
galv/apis/paths/arbitrary_files_describe_.py
galv/apis/paths/arbitrary_files_id_.py
galv/apis/paths/arbitrary_files_id_file_.py
galv/apis/paths/cell_chemistries_.py
galv/apis/paths/cell_chemistries_describe_.py
galv/apis/paths/cell_families_.py
galv/apis/paths/cell_families_describe_.py
galv/apis/paths/cell_families_id_.py
galv/apis/paths/cell_form_factors_.py
galv/apis/paths/cell_form_factors_describe_.py
galv/apis/paths/cell_manufacturers_.py
galv/apis/paths/cell_manufacturers_describe_.py
galv/apis/paths/cell_models_.py
galv/apis/paths/cell_models_describe_.py
galv/apis/paths/cells_.py
galv/apis/paths/cells_describe_.py
galv/apis/paths/cells_id_.py
galv/apis/paths/cells_id_rdf_.py
galv/apis/paths/column_mappings_.py
galv/apis/paths/column_mappings_describe_.py
galv/apis/paths/column_mappings_id_.py
galv/apis/paths/column_types_.py
galv/apis/paths/column_types_describe_.py
galv/apis/paths/column_types_id_.py
galv/apis/paths/create_token_.py
galv/apis/paths/cycler_tests_.py
galv/apis/paths/cycler_tests_describe_.py
galv/apis/paths/cycler_tests_id_.py
galv/apis/paths/dump_id_.py
galv/apis/paths/equipment_.py
galv/apis/paths/equipment_describe_.py
galv/apis/paths/equipment_families_.py
galv/apis/paths/equipment_families_describe_.py
galv/apis/paths/equipment_families_id_.py
galv/apis/paths/equipment_id_.py
galv/apis/paths/equipment_manufacturers_.py
galv/apis/paths/equipment_manufacturers_describe_.py
galv/apis/paths/equipment_models_.py
galv/apis/paths/equipment_models_describe_.py
galv/apis/paths/equipment_types_.py
galv-2.11.4.dist-info/LICENCE
galv-2.11.4.dist-info/METADATA
galv-2.11.4.dist-info/WHEEL
galv-2.11.4.dist-info/top_level.txt
galv-2.11.4.dist-info/RECORD
