Metadata-Version: 2.1
Name: galv
Version: 2.11.4
Summary: Battery Data API
Home-page: 
Author: OpenAPI Generator community
Author-email: martin.robinson@cs.ox.ac.uk
License: Apache 2.0
Keywords: OpenAPI,OpenAPI-Generator,Battery Data API
Requires-Python: >=3.7
License-File: LICENCE
Requires-Dist: certifi >=14.5.14
Requires-Dist: frozendict ~=2.3.4
Requires-Dist: python-dateutil ~=2.7.0
Requires-Dist: setuptools >=21.0.0
Requires-Dist: typing-extensions ~=4.3.0
Requires-Dist: urllib3 ~=1.26.7
